scanner3d/__init__.py
scanner3d/py.typed
scanner3d/afs/__init__.py
scanner3d/afs/album.py
scanner3d/afs/frame.py
scanner3d/afs/frame_meta.py
scanner3d/afs/i_shot_meta.py
scanner3d/afs/i_shot_result.py
scanner3d/afs/plotter.py
scanner3d/afs/shot.py
scanner3d/analysis/__init__.py
scanner3d/analysis/fft_psf_from_shot.py
scanner3d/analysis/zernike_data.py
scanner3d/analysis/zernike_meta.py
scanner3d/camera3d/__init__.py
scanner3d/camera3d/camera3d.py
scanner3d/camera3d/camera_under_test.py
scanner3d/geo/__init__.py
scanner3d/geo/position.py
scanner3d/geo/z_range.py
scanner3d/h5/__init__.py
scanner3d/h5/camera_ref_to_h5.py
scanner3d/h5/grid_meta_to_h5.py
scanner3d/h5/h5aid.py
scanner3d/h5/album/album_format.py
scanner3d/h5/album/album_load.py
scanner3d/h5/album/album_save.py
scanner3d/h5/album/album_settings_to_h5.py
scanner3d/h5/album/album_to_h5.py
scanner3d/h5/frame/frame_format.py
scanner3d/h5/frame/frame_read.py
scanner3d/h5/frame/frame_write.py
scanner3d/h5/ray_batch/ray_batch_format.py
scanner3d/h5/ray_batch/ray_batch_read.py
scanner3d/h5/ray_batch/ray_batch_write.py
scanner3d/h5/ray_batch/ray_batches_format.py
scanner3d/h5/ray_batch/ray_batches_load.py
scanner3d/h5/ray_batch/ray_batches_save.py
scanner3d/h5/shot/shot_factories.py
scanner3d/ray_trace/__init__.py
scanner3d/ray_trace/aid.py
scanner3d/ray_trace/generic_ray_tracer.py
scanner3d/ray_trace/ray_batch.py
scanner3d/ray_trace/ray_batch_type.py
scanner3d/ray_trace/ray_batches.py
scanner3d/ray_trace/raytrace_settings.py
scanner3d/ray_trace/recipe.py
scanner3d/ray_trace/trace_method.py
scanner3d/scanner/__init__.py
scanner3d/scanner/scanner.py
scanner3d/scanner/scanner_ref.py
scanner3d/scanners/Eva1.py
scanner3d/scanners/Eva2A.py
scanner3d/scanners/Eva2B.py
scanner3d/scanners/Eva2C.py
scanner3d/scanners/Leo.py
scanner3d/scanners/Leo2.py
scanner3d/scanners/ScannersDB.py
scanner3d/scanners/ScannersDB.pyi
scanner3d/scanners/Spider2.py
scanner3d/scanners/Spider2ProB.py
scanner3d/scanners/Spider2ProC.py
scanner3d-0.4.7.dist-info/licenses/LICENSE
scanner3d-0.4.7.dist-info/METADATA
scanner3d-0.4.7.dist-info/WHEEL
scanner3d-0.4.7.dist-info/top_level.txt
scanner3d-0.4.7.dist-info/RECORD
