Metadata-Version: 2.4
Name: scanner3d
Version: 0.4.7
Summary: 3D scanner tools
Author-email: Anton Sharapov <sharapov.anton@gmail.com>
License-Expression: MIT
Project-URL: Homepage, https://github.com/SharapovAnton/scanner3d
Project-URL: Source, https://github.com/SharapovAnton/scanner3d
Project-URL: Issues, https://github.com/SharapovAnton/scanner3d/issues
Classifier: Programming Language :: Python :: 3
Classifier: Programming Language :: Python :: 3 :: Only
Classifier: Operating System :: OS Independent
Classifier: Topic :: Software Development :: Libraries
Classifier: Typing :: Typed
Requires-Python: >=3.8
License-File: LICENSE
Requires-Dist: numpy>=1.23
Requires-Dist: allytools>=0.5.3
Requires-Dist: imagera>=0.3.2
Requires-Dist: lensguild>=0.5.1
Requires-Dist: zempy>=0.6.0
Requires-Dist: h5py>=3.15.1
Requires-Dist: clr_loader>=0.2.7
Requires-Dist: opticulator>=0.2.0
Requires-Dist: isensor>=0.2.0
Requires-Dist: gosti>=0.3.2
Provides-Extra: dev
Requires-Dist: pytest; extra == "dev"
Provides-Extra: qa
Requires-Dist: tox; extra == "qa"
Provides-Extra: gui
Requires-Dist: PyQt5; extra == "gui"
Dynamic: license-file
